turp.py
turp-0.0.2.dist-info/METADATA
turp-0.0.2.dist-info/WHEEL
turp-0.0.2.dist-info/licenses/LICENSE
turp-0.0.2.dist-info/RECORD
