Metadata-Version: 2.1
Name: turp
Version: 0.0.2
Summary: Python package to calculate the range of cassettes needed for transurethral resection specimens
Author-email: Gabe Dumbrille <gndumbri@gmail.com>
License-File: LICENSE
Classifier: License :: OSI Approved :: MIT License
Classifier: Operating System :: OS Independent
Classifier: Programming Language :: Python :: 3.9
Requires-Python: >=3.7
